<Properties StartupConfiguration="{7CC2B9C7-3016-4A2A-9591-6A24BDD791FF}|Default">
  <MonoDevelop.Ide.Workbench>
    <Pads>
      <Pad Id="ProjectPad">
        <State name="__root__">
          <Node name="StudentAPI" expanded="True">
            <Node name="StudentAPI" expanded="True">
              <Node name="Controllers" expanded="True">
                <Node name="StudentController.cs" selected="True" />
              </Node>
              <Node name="Repository" expanded="True" />
            </Node>
          </Node>
        </State>
      </Pad>
    </Pads>
  </MonoDevelop.Ide.Workbench>
  <MonoDevelop.Ide.DebuggingService.PinnedWatches />
  <MonoDevelop.Ide.ItemProperties.StudentAPI PreferredExecutionTarget="/Applications/Safari.app" />
  <MonoDevelop.Ide.Workspace ActiveConfiguration="Debug" />
  <MonoDevelop.Ide.DebuggingService.Breakpoints>
    <BreakpointStore />
  </MonoDevelop.Ide.DebuggingService.Breakpoints>
  <MultiItemStartupConfigurations />
</Properties>